LICENSE
MANIFEST.in
ecr_scan_reporter/__init__.py
ecr_scan_reporter/cli.py
ecr_scan_reporter/common.py
ecr_scan_reporter/ecr_scan_reporter.py
ecr_scan_reporter/images_scanner.py
ecr_scan_reporter/lambda_functions.py
ecr_scan_reporter/repos_scanner.py
ecr_scan_reporter/services_scanner.py
ecr_scan_reporter-0.4.8.dist-info/LICENSE
ecr_scan_reporter-0.4.8.dist-info/METADATA
ecr_scan_reporter-0.4.8.dist-info/WHEEL
ecr_scan_reporter-0.4.8.dist-info/entry_points.txt
ecr_scan_reporter-0.4.8.dist-info/RECORD
