Metadata-Version: 2.1
Name: ecr-scan-reporter
Version: 0.4.8
Summary: Stay on top of your docker images security vulnerabilities in AWS ECR
License: MPL-2.0
Keywords: aws-ecr,security,vulnerabilities
Author: John Preston
Author-email: john@compose-x.io
Requires-Python: >=3.8,<4.0
Classifier: Development Status :: 2 - Pre-Alpha
Classifier: Intended Audience :: Developers
Classifier: License :: OSI Approved
Classifier: Natural Language :: English
Classifier: Programming Language :: Python :: 3
Classifier: Programming Language :: Python :: 3.8
Classifier: Programming Language :: Python :: 3.9
Classifier: Programming Language :: Python :: 3.10
Classifier: Programming Language :: Python :: 3.11
Classifier: Programming Language :: Python :: 3
Classifier: Programming Language :: Python :: 3.10
Classifier: Programming Language :: Python :: 3.8
Classifier: Programming Language :: Python :: 3.9
Requires-Dist: boto3 (>=1.22,<2.0)
Requires-Dist: compose-x-common (>=1.2,<2.0)
Requires-Dist: pytz (>=2023.3,<2024.0)
